telebot_router/__init__.py
telebot_router/filters.py
telebot_router-2.0.0.dist-info/METADATA
telebot_router-2.0.0.dist-info/WHEEL
telebot_router-2.0.0.dist-info/top_level.txt
telebot_router-2.0.0.dist-info/RECORD
